{
    "1": {
        "_id": 1,
        "_date": "Mon Apr 01 2019",
        "_timestamp": 1554087399439,
        "description": "mbb grad",
        "isStarred": false,
        "boards": [
            "My Board"
        ],
        "_isTask": true,
        "isComplete": true,
        "inProgress": false,
        "priority": 1
    },
    "2": {
        "_id": 2,
        "_date": "Mon Apr 01 2019",
        "_timestamp": 1554088611002,
        "description": "cv + usc experiences",
        "isStarred": false,
        "boards": [
            "@grad"
        ],
        "_isTask": true,
        "isComplete": true,
        "inProgress": false,
        "priority": 1
    },
    "3": {
        "_id": 3,
        "_date": "Mon Apr 01 2019",
        "_timestamp": 1554087399439,
        "description": "onboarding flow revise",
        "isStarred": true,
        "boards": [
            "@glow"
        ],
        "_isTask": true,
        "isComplete": true,
        "inProgress": false,
        "priority": 1
    },
    "4": {
        "_id": 4,
        "_date": "Mon Apr 01 2019",
        "_timestamp": 1554088611002,
        "description": "cv + usc experiences",
        "isStarred": false,
        "boards": [
            "@grad"
        ],
        "_isTask": true,
        "isComplete": true,
        "inProgress": false,
        "priority": 1
    },
    "5": {
        "_id": 5,
        "_date": "Mon Apr 01 2019",
        "_timestamp": 1554088820391,
        "description": "sop last para",
        "isStarred": false,
        "boards": [
            "@grad"
        ],
        "_isTask": true,
        "isComplete": true,
        "inProgress": false,
        "priority": 1
    },
    "6": {
        "_id": 6,
        "_date": "Mon Apr 01 2019",
        "_timestamp": 1554088926812,
        "description": "glowcare login layout",
        "isStarred": false,
        "boards": [
            "@glow"
        ],
        "_isTask": true,
        "isComplete": true,
        "inProgress": false,
        "priority": 1
    },
    "7": {
        "_id": 7,
        "_date": "Mon Apr 01 2019",
        "_timestamp": 1554088611002,
        "description": "sync dotfiles with crontab",
        "isStarred": false,
        "boards": [
            "@dev"
        ],
        "_isTask": true,
        "isComplete": true,
        "inProgress": false,
        "priority": 1
    },
    "8": {
        "_id": 8,
        "_date": "Tue Apr 02 2019",
        "_timestamp": 1554174963783,
        "description": "charge toothbrush",
        "isStarred": false,
        "boards": [
            "@personal"
        ],
        "_isTask": true,
        "isComplete": true,
        "inProgress": false,
        "priority": 1
    },
    "9": {
        "_id": 9,
        "_date": "Wed Apr 03 2019",
        "_timestamp": 1554262370412,
        "description": "checklist-result",
        "isStarred": false,
        "boards": [
            "@glow"
        ],
        "_isTask": false
    },
    "10": {
        "_id": 10,
        "_date": "Tue Apr 02 2019",
        "_timestamp": 1554174963783,
        "description": "sjtu dorm",
        "isStarred": false,
        "boards": [
            "@personal"
        ],
        "_isTask": true,
        "isComplete": true,
        "inProgress": false,
        "priority": 1
    },
    "11": {
        "_id": 11,
        "_date": "Tue Apr 02 2019",
        "_timestamp": 1554174963783,
        "description": "create NTU application account",
        "isStarred": false,
        "boards": [
            "@grad"
        ],
        "_isTask": true,
        "isComplete": true,
        "inProgress": false,
        "priority": 1
    },
    "12": {
        "_id": 12,
        "_date": "Wed Apr 03 2019",
        "_timestamp": 1554263261207,
        "description": "branch: appointment",
        "isStarred": false,
        "boards": [
            "@glow"
        ],
        "_isTask": false
    },
    "13": {
        "_id": 13,
        "_date": "Tue Apr 02 2019",
        "_timestamp": 1554174963783,
        "description": "integrate with lab result detail",
        "isStarred": false,
        "boards": [
            "@glow"
        ],
        "_isTask": true,
        "isComplete": false,
        "inProgress": false,
        "priority": 1
    },
    "14": {
        "_id": 14,
        "_date": "Wed Apr 03 2019",
        "_timestamp": 1554261392376,
        "description": "appointment ui",
        "isStarred": false,
        "boards": [
            "@glow"
        ],
        "_isTask": true,
        "isComplete": true,
        "inProgress": false,
        "priority": "2"
    },
    "15": {
        "_id": 15,
        "_date": "Wed Apr 03 2019",
        "_timestamp": 1554262370412,
        "description": "checklist-result",
        "isStarred": false,
        "boards": [
            "@glow"
        ],
        "_isTask": false
    },
    "16": {
        "_id": 16,
        "_date": "Thu Apr 04 2019",
        "_timestamp": 1554355739030,
        "description": "appointment provider in lab schedules",
        "isStarred": false,
        "boards": [
            "@glow"
        ],
        "_isTask": true,
        "isComplete": true,
        "inProgress": false,
        "priority": 1
    },
    "17": {
        "_id": 17,
        "_date": "Mon Apr 08 2019",
        "_timestamp": 1554691576471,
        "description": "review vita pr",
        "isStarred": false,
        "boards": [
            "@glow"
        ],
        "_isTask": true,
        "isComplete": true,
        "inProgress": false,
        "priority": 1
    },
    "18": {
        "_id": 18,
        "_date": "Mon Apr 08 2019",
        "_timestamp": 1554691576471,
        "description": "checklist -> lab results",
        "isStarred": false,
        "boards": [
            "@glow"
        ],
        "_isTask": true,
        "isComplete": true,
        "inProgress": false,
        "priority": 1
    },
    "19": {
        "_id": 19,
        "_date": "Mon Apr 08 2019",
        "_timestamp": 1554711136008,
        "description": "implement smart priority list for taskbook",
        "isStarred": false,
        "boards": [
            "@idea"
        ],
        "_isTask": true,
        "isComplete": true,
        "inProgress": false,
        "priority": 1
    },
    "20": {
        "_id": 20,
        "_date": "Mon Apr 08 2019",
        "_timestamp": 1554711136008,
        "description": "implement tab completion/alias/help for taskbook",
        "isStarred": false,
        "boards": [
            "@idea"
        ],
        "_isTask": true,
        "isComplete": true,
        "inProgress": false,
        "priority": 1
    },
    "21": {
        "_id": 21,
        "_date": "Tue Apr 02 2019",
        "_timestamp": 1554174963783,
        "description": "rl dengmiao",
        "isStarred": false,
        "boards": [
            "@grad"
        ],
        "_isTask": true,
        "isComplete": true,
        "inProgress": false,
        "priority": 1
    },
    "22": {
        "_id": 22,
        "_date": "Mon Apr 08 2019",
        "_timestamp": 1554714420550,
        "description": "onboarding questions server struct with Jeff (UI?)",
        "isStarred": false,
        "boards": [
            "@glow"
        ],
        "_isTask": true,
        "isComplete": true,
        "inProgress": false,
        "priority": 1
    },
    "23": {
        "_id": 23,
        "_date": "Tue Apr 09 2019",
        "_timestamp": 1554776333224,
        "description": "onboarding questions UI",
        "isStarred": false,
        "boards": [
            "@glow"
        ],
        "_isTask": true,
        "isComplete": false,
        "inProgress": false,
        "priority": 1
    },
    "24": {
        "_id": 24,
        "_date": "Mon Apr 08 2019",
        "_timestamp": 1554691576471,
        "description": "change proposal",
        "isStarred": false,
        "boards": [
            "@gsoc"
        ],
        "_isTask": true,
        "isComplete": true,
        "inProgress": false,
        "priority": 1
    },
    "25": {
        "_id": 25,
        "_date": "Tue Apr 09 2019",
        "_timestamp": 1554776333224,
        "description": "submit proposal",
        "isStarred": false,
        "boards": [
            "@gsoc"
        ],
        "_isTask": true,
        "isComplete": true,
        "inProgress": false,
        "priority": 1
    }
}